Workbook
Name _96.12.30: #REF!
Name ARCHITECTURAL: #REF!
Name bbb: #REF!
Name CIVIL: #REF!
Name ELECTRICAL: #REF!
Name FIRE: #REF!
Name fx: #REF!
Name FX_Er_DEM: #REF!
Name FX_rate: #REF!
Name HV: #REF!
Name jkjkjkj: #REF!
Name MECHANICAL: #REF!
Name nnnnm: #REF!
Name SITEWORKS: #REF!
Name STRUCTURAL: #REF!
Name UFPrn20160217113411: #REF!
Name vvv: #REF!
Name X980210_payment_printing_List: #REF!
Name 科目余额表: #REF!
Name 明细分类账: #REF!

Sheet 看板
B2: 底稿进度概览： | C2: =TODAY() -> 46176
B3: 项目维度
B4: 服务单号 | C4: 项目名称 | D4: 预算 | E4: 实际 | F4: 剩余 | G4: 底稿数量 | H4: =底稿进度!K2 -> BKD | I4: =底稿进度!L2 -> TOD | J4: cut off | K4: =底稿进度!N2 -> 其他程序 | L4: 已完成 | M4: FIC已复核 | N4: EIC已复核 | O4: =底稿进度!V2 -> 首次交付 | P4: =底稿进度!W2 -> 最终交付 | Q4: 距离首交倒计时（天）
B5: 47115251- EDC251017001 | C5: 瑞云冷链 | D5: 1238.6 | E5: =_xlfn.XLOOKUP(B5,'[1]项目工时-项目口径'!$B:$B,'[1]项目工时-项目口径'!$J:$J) -> 814 | F5: =D5-E5 -> 424.6 | G5: =COUNTIF(底稿进度!B:B,看板!B5) -> 3 | H5: =COUNTIFS(底稿进度!B:B,看板!B5,底稿进度!K:K,"Y") -> 3 | I5: =COUNTIFS(底稿进度!B:B,看板!B5,底稿进度!L:L,"Y") -> 0 | J5: =COUNTIFS(底稿进度!B:B,看板!B5,底稿进度!M:M,"Y") -> 3 | K5: =COUNTIFS(底稿进度!B:B,看板!B5,底稿进度!N:N,"Y") -> 3 | L5: =COUNTIFS(底稿进度!B:B,看板!B5,底稿进度!S:S,"Y") -> 3 | M5: =COUNTIFS(底稿进度!B:B,看板!B5,底稿进度!T:T,"Y") -> 3 | N5: =COUNTIFS(底稿进度!B:B,看板!B5,底稿进度!U:U,"Y") -> 3 | O5: =COUNTIFS(底稿进度!B:B,看板!B5,底稿进度!V:V,"Y") -> 3 | P5: =COUNTIFS(底稿进度!B:B,看板!B5,底稿进度!W:W,"Y") -> 3 | Q5: =IF((_xlfn.XLOOKUP(B5,项目基础信息!B:B,项目基础信息!G:G)-$C$2)<0,"不适用",(_xlfn.XLOOKUP(B5,项目基础信息!B:B,项目基础信息!G:G)-$C$2)) -> 不适用
B6: 47035622- EDC250625001 | C6: PAOB | D6: 667.7 | E6: =_xlfn.XLOOKUP(B6,'[1]项目工时-项目口径'!$B:$B,'[1]项目工时-项目口径'!$J:$J) -> 315.5 | F6: =D6-E6 -> 352.2 | G6: =COUNTIF(底稿进度!B:B,看板!B6) -> 4 | H6: =COUNTIFS(底稿进度!B:B,看板!B6,底稿进度!K:K,"Y") -> 4 | I6: =COUNTIFS(底稿进度!B:B,看板!B6,底稿进度!L:L,"Y") -> 1 | J6: =COUNTIFS(底稿进度!B:B,看板!B6,底稿进度!M:M,"Y") -> 1 | K6: =COUNTIFS(底稿进度!B:B,看板!B6,底稿进度!N:N,"Y") -> 4 | L6: =COUNTIFS(底稿进度!B:B,看板!B6,底稿进度!S:S,"Y") -> 4 | M6: =COUNTIFS(底稿进度!B:B,看板!B6,底稿进度!T:T,"Y") -> 4 | N6: =COUNTIFS(底稿进度!B:B,看板!B6,底稿进度!U:U,"Y") -> 4 | O6: =COUNTIFS(底稿进度!B:B,看板!B6,底稿进度!V:V,"Y") -> 4 | P6: =COUNTIFS(底稿进度!B:B,看板!B6,底稿进度!W:W,"Y") -> 4 | Q6: =IF((_xlfn.XLOOKUP(B6,项目基础信息!B:B,项目基础信息!G:G)-$C$2)<0,"不适用",(_xlfn.XLOOKUP(B6,项目基础信息!B:B,项目基础信息!G:G)-$C$2)) -> 不适用
B7: 47096395- EDC250620001 | C7: 香奈儿 | D7: 265.65 | E7: =_xlfn.XLOOKUP(B7,'[1]项目工时-项目口径'!$B:$B,'[1]项目工时-项目口径'!$J:$J) -> 255 | F7: =D7-E7 -> 10.65 | G7: =COUNTIF(底稿进度!B:B,看板!B7) -> 11 | H7: =COUNTIFS(底稿进度!B:B,看板!B7,底稿进度!K:K,"Y") -> 11 | I7: =COUNTIFS(底稿进度!B:B,看板!B7,底稿进度!L:L,"Y") -> 0 | J7: =COUNTIFS(底稿进度!B:B,看板!B7,底稿进度!M:M,"Y") -> 1 | K7: =COUNTIFS(底稿进度!B:B,看板!B7,底稿进度!N:N,"Y") -> 1 | L7: =COUNTIFS(底稿进度!B:B,看板!B7,底稿进度!S:S,"Y") -> 11 | M7: =COUNTIFS(底稿进度!B:B,看板!B7,底稿进度!T:T,"Y") -> 11 | N7: =COUNTIFS(底稿进度!B:B,看板!B7,底稿进度!U:U,"Y") -> 11 | O7: =COUNTIFS(底稿进度!B:B,看板!B7,底稿进度!V:V,"Y") -> 11 | P7: =COUNTIFS(底稿进度!B:B,看板!B7,底稿进度!W:W,"Y") -> 11 | Q7: =IF((_xlfn.XLOOKUP(B7,项目基础信息!B:B,项目基础信息!G:G)-$C$2)<0,"不适用",(_xlfn.XLOOKUP(B7,项目基础信息!B:B,项目基础信息!G:G)-$C$2)) -> 不适用
B8: 47095110- EDC250620001 | C8: DNE | D8: 1882.1 | E8: =_xlfn.XLOOKUP(B8,'[1]项目工时-项目口径'!$B:$B,'[1]项目工时-项目口径'!$J:$J) -> 1879.5 | F8: =D8-E8 -> 2.6 | G8: =COUNTIF(底稿进度!B:B,看板!B8) -> 94 | H8: =COUNTIFS(底稿进度!B:B,看板!B8,底稿进度!K:K,"Y") -> 94 | I8: =COUNTIFS(底稿进度!B:B,看板!B8,底稿进度!L:L,"Y") -> 81 | J8: =COUNTIFS(底稿进度!B:B,看板!B8,底稿进度!M:M,"Y") -> 3 | K8: =COUNTIFS(底稿进度!B:B,看板!B8,底稿进度!N:N,"Y") -> 92 | L8: =COUNTIFS(底稿进度!B:B,看板!B8,底稿进度!S:S,"Y") -> 94 | M8: =COUNTIFS(底稿进度!B:B,看板!B8,底稿进度!T:T,"Y") -> 94 | N8: =COUNTIFS(底稿进度!B:B,看板!B8,底稿进度!U:U,"Y") -> 94 | O8: =COUNTIFS(底稿进度!B:B,看板!B8,底稿进度!V:V,"Y") -> 94 | P8: =COUNTIFS(底稿进度!B:B,看板!B8,底稿进度!W:W,"Y") -> 94 | Q8: =IF((_xlfn.XLOOKUP(B8,项目基础信息!B:B,项目基础信息!G:G)-$C$2)<0,"不适用",(_xlfn.XLOOKUP(B8,项目基础信息!B:B,项目基础信息!G:G)-$C$2)) -> 不适用
B9: 47095951- EDC250620001 | C9: 江苏瑞科 | D9: 201.3 | E9: =_xlfn.XLOOKUP(B9,'[1]项目工时-项目口径'!$B:$B,'[1]项目工时-项目口径'!$J:$J) -> 187.5 | F9: =D9-E9 -> 13.8 | G9: =COUNTIF(底稿进度!B:B,看板!B9) -> 15 | H9: =COUNTIFS(底稿进度!B:B,看板!B9,底稿进度!K:K,"Y") -> 15 | I9: =COUNTIFS(底稿进度!B:B,看板!B9,底稿进度!L:L,"Y") -> 1 | J9: =COUNTIFS(底稿进度!B:B,看板!B9,底稿进度!M:M,"Y") -> 5 | K9: =COUNTIFS(底稿进度!B:B,看板!B9,底稿进度!N:N,"Y") -> 6 | L9: =COUNTIFS(底稿进度!B:B,看板!B9,底稿进度!S:S,"Y") -> 15 | M9: =COUNTIFS(底稿进度!B:B,看板!B9,底稿进度!T:T,"Y") -> 15 | N9: =COUNTIFS(底稿进度!B:B,看板!B9,底稿进度!U:U,"Y") -> 15 | O9: =COUNTIFS(底稿进度!B:B,看板!B9,底稿进度!V:V,"Y") -> 15 | P9: =COUNTIFS(底稿进度!B:B,看板!B9,底稿进度!W:W,"Y") -> 15 | Q9: =IF((_xlfn.XLOOKUP(B9,项目基础信息!B:B,项目基础信息!G:G)-$C$2)<0,"不适用",(_xlfn.XLOOKUP(B9,项目基础信息!B:B,项目基础信息!G:G)-$C$2)) -> 不适用
B10: 47095577- EDC250530001 | C10: H3C | D10: 565.62 | E10: =_xlfn.XLOOKUP(B10,'[1]项目工时-项目口径'!$B:$B,'[1]项目工时-项目口径'!$J:$J) -> 604 | F10: =D10-E10 -> -38.38 | G10: =COUNTIF(底稿进度!B:B,看板!B10) -> 42 | H10: =COUNTIFS(底稿进度!B:B,看板!B10,底稿进度!K:K,"Y") -> 42 | I10: =COUNTIFS(底稿进度!B:B,看板!B10,底稿进度!L:L,"Y") -> 3 | J10: =COUNTIFS(底稿进度!B:B,看板!B10,底稿进度!M:M,"Y") -> 24 | K10: =COUNTIFS(底稿进度!B:B,看板!B10,底稿进度!N:N,"Y") -> 39 | L10: =COUNTIFS(底稿进度!B:B,看板!B10,底稿进度!S:S,"Y") -> 42 | M10: =COUNTIFS(底稿进度!B:B,看板!B10,底稿进度!T:T,"Y") -> 42 | N10: =COUNTIFS(底稿进度!B:B,看板!B10,底稿进度!U:U,"Y") -> 42 | O10: =COUNTIFS(底稿进度!B:B,看板!B10,底稿进度!V:V,"Y") -> 42 | P10: =COUNTIFS(底稿进度!B:B,看板!B10,底稿进度!W:W,"Y") -> 42 | Q10: =IF((_xlfn.XLOOKUP(B10,项目基础信息!B:B,项目基础信息!G:G)-$C$2)<0,"不适用",(_xlfn.XLOOKUP(B10,项目基础信息!B:B,项目基础信息!G:G)-$C$2)) -> 不适用
B11: 47094516- EDC250620002 | C11: 瀚瑞森 | D11: 45.1 | E11: =_xlfn.XLOOKUP(B11,'[1]项目工时-项目口径'!$B:$B,'[1]项目工时-项目口径'!$J:$J) -> 42.5 | F11: =D11-E11 -> 2.6 | G11: =COUNTIF(底稿进度!B:B,看板!B11) -> 3 | H11: =COUNTIFS(底稿进度!B:B,看板!B11,底稿进度!K:K,"Y") -> 3 | I11: =COUNTIFS(底稿进度!B:B,看板!B11,底稿进度!L:L,"Y") -> 1 | J11: =COUNTIFS(底稿进度!B:B,看板!B11,底稿进度!M:M,"Y") -> 1 | K11: =COUNTIFS(底稿进度!B:B,看板!B11,底稿进度!N:N,"Y") -> 3 | L11: =COUNTIFS(底稿进度!B:B,看板!B11,底稿进度!S:S,"Y") -> 3 | M11: =COUNTIFS(底稿进度!B:B,看板!B11,底稿进度!T:T,"Y") -> 3 | N11: =COUNTIFS(底稿进度!B:B,看板!B11,底稿进度!U:U,"Y") -> 3 | O11: =COUNTIFS(底稿进度!B:B,看板!B11,底稿进度!V:V,"Y") -> 3 | P11: =COUNTIFS(底稿进度!B:B,看板!B11,底稿进度!W:W,"Y") -> 3 | Q11: =IF((_xlfn.XLOOKUP(B11,项目基础信息!B:B,项目基础信息!G:G)-$C$2)<0,"不适用",(_xlfn.XLOOKUP(B11,项目基础信息!B:B,项目基础信息!G:G)-$C$2)) -> 不适用
B12: 47097374- EDC250613002 | C12: 乐尔幸 | D12: 148.5 | E12: =_xlfn.XLOOKUP(B12,'[1]项目工时-项目口径'!$B:$B,'[1]项目工时-项目口径'!$J:$J) -> 102 | F12: =D12-E12 -> 46.5 | G12: =COUNTIF(底稿进度!B:B,看板!B12) -> 8 | H12: =COUNTIFS(底稿进度!B:B,看板!B12,底稿进度!K:K,"Y") -> 8 | I12: =COUNTIFS(底稿进度!B:B,看板!B12,底稿进度!L:L,"Y") -> 2 | J12: =COUNTIFS(底稿进度!B:B,看板!B12,底稿进度!M:M,"Y") -> 2 | K12: =COUNTIFS(底稿进度!B:B,看板!B12,底稿进度!N:N,"Y") -> 4 | L12: =COUNTIFS(底稿进度!B:B,看板!B12,底稿进度!S:S,"Y") -> 8 | M12: =COUNTIFS(底稿进度!B:B,看板!B12,底稿进度!T:T,"Y") -> 8 | N12: =COUNTIFS(底稿进度!B:B,看板!B12,底稿进度!U:U,"Y") -> 8 | O12: =COUNTIFS(底稿进度!B:B,看板!B12,底稿进度!V:V,"Y") -> 8 | P12: =COUNTIFS(底稿进度!B:B,看板!B12,底稿进度!W:W,"Y") -> 8 | Q12: =IF((_xlfn.XLOOKUP(B12,项目基础信息!B:B,项目基础信息!G:G)-$C$2)<0,"不适用",(_xlfn.XLOOKUP(B12,项目基础信息!B:B,项目基础信息!G:G)-$C$2)) -> 不适用
B13: 47095936- EDC260401002 | C13: 李尔汽车部件 | D13: 36.3 | E13: =_xlfn.XLOOKUP(B13,'[1]项目工时-项目口径'!$B:$B,'[1]项目工时-项目口径'!$J:$J) -> 32 | F13: =D13-E13 -> 4.3 | G13: =COUNTIF(底稿进度!B:B,看板!B13) -> 3 | H13: =COUNTIFS(底稿进度!B:B,看板!B13,底稿进度!K:K,"Y") -> 3 | I13: =COUNTIFS(底稿进度!B:B,看板!B13,底稿进度!L:L,"Y") -> 0 | J13: =COUNTIFS(底稿进度!B:B,看板!B13,底稿进度!M:M,"Y") -> 0 | K13: =COUNTIFS(底稿进度!B:B,看板!B13,底稿进度!N:N,"Y") -> 0 | L13: =COUNTIFS(底稿进度!B:B,看板!B13,底稿进度!S:S,"Y") -> 3 | M13: =COUNTIFS(底稿进度!B:B,看板!B13,底稿进度!T:T,"Y") -> 3 | N13: =COUNTIFS(底稿进度!B:B,看板!B13,底稿进度!U:U,"Y") -> 3 | O13: =COUNTIFS(底稿进度!B:B,看板!B13,底稿进度!V:V,"Y") -> 3 | P13: =COUNTIFS(底稿进度!B:B,看板!B13,底稿进度!W:W,"Y") -> 3 | Q13: =IF((_xlfn.XLOOKUP(B13,项目基础信息!B:B,项目基础信息!G:G)-$C$2)<0,"不适用",(_xlfn.XLOOKUP(B13,项目基础信息!B:B,项目基础信息!G:G)-$C$2)) -> 不适用
B14: 47095226- EDC260403001 | C14: 李尔中国投资 | D14: 41.8 | E14: =_xlfn.XLOOKUP(B14,'[1]项目工时-项目口径'!$B:$B,'[1]项目工时-项目口径'!$J:$J) -> 34 | F14: =D14-E14 -> 7.8 | G14: =COUNTIF(底稿进度!B:B,看板!B14) -> 4 | H14: =COUNTIFS(底稿进度!B:B,看板!B14,底稿进度!K:K,"Y") -> 4 | I14: =COUNTIFS(底稿进度!B:B,看板!B14,底稿进度!L:L,"Y") -> 0 | J14: =COUNTIFS(底稿进度!B:B,看板!B14,底稿进度!M:M,"Y") -> 0 | K14: =COUNTIFS(底稿进度!B:B,看板!B14,底稿进度!N:N,"Y") -> 0 | L14: =COUNTIFS(底稿进度!B:B,看板!B14,底稿进度!S:S,"Y") -> 4 | M14: =COUNTIFS(底稿进度!B:B,看板!B14,底稿进度!T:T,"Y") -> 4 | N14: =COUNTIFS(底稿进度!B:B,看板!B14,底稿进度!U:U,"Y") -> 4 | O14: =COUNTIFS(底稿进度!B:B,看板!B14,底稿进度!V:V,"Y") -> 4 | P14: =COUNTIFS(底稿进度!B:B,看板!B14,底稿进度!W:W,"Y") -> 4 | Q14: =IF((_xlfn.XLOOKUP(B14,项目基础信息!B:B,项目基础信息!G:G)-$C$2)<0,"不适用",(_xlfn.XLOOKUP(B14,项目基础信息!B:B,项目基础信息!G:G)-$C$2)) -> 不适用
B15: 47076663- EDC260119001 | C15: 紫光展锐 | D15: 494.56 | E15: =_xlfn.XLOOKUP(B15,'[1]项目工时-项目口径'!$B:$B,'[1]项目工时-项目口径'!$J:$J) -> 485 | F15: =D15-E15 -> 9.56 | G15: =COUNTIF(底稿进度!B:B,看板!B15) -> 48 | H15: =COUNTIFS(底稿进度!B:B,看板!B15,底稿进度!K:K,"Y") -> 48 | I15: =COUNTIFS(底稿进度!B:B,看板!B15,底稿进度!L:L,"Y") -> 4 | J15: =COUNTIFS(底稿进度!B:B,看板!B15,底稿进度!M:M,"Y") -> 1 | K15: =COUNTIFS(底稿进度!B:B,看板!B15,底稿进度!N:N,"Y") -> 43 | L15: =COUNTIFS(底稿进度!B:B,看板!B15,底稿进度!S:S,"Y") -> 48 | M15: =COUNTIFS(底稿进度!B:B,看板!B15,底稿进度!T:T,"Y") -> 48 | N15: =COUNTIFS(底稿进度!B:B,看板!B15,底稿进度!U:U,"Y") -> 48 | O15: =COUNTIFS(底稿进度!B:B,看板!B15,底稿进度!V:V,"Y") -> 48 | P15: =COUNTIFS(底稿进度!B:B,看板!B15,底稿进度!W:W,"Y") -> 48 | Q15: =IF((_xlfn.XLOOKUP(B15,项目基础信息!B:B,项目基础信息!G:G)-$C$2)<0,"不适用",(_xlfn.XLOOKUP(B15,项目基础信息!B:B,项目基础信息!G:G)-$C$2)) -> 不适用
B16: 47137340- EDC260527002 | C16: 万帮数字 | D16: 729.6 | F16: =D16-E16 -> 729.6 | G16: =COUNTIF(底稿进度!B:B,看板!B16) -> 4 | H16: =COUNTIFS(底稿进度!B:B,看板!B16,底稿进度!K:K,"Y") -> 0 | I16: =COUNTIFS(底稿进度!B:B,看板!B16,底稿进度!L:L,"Y") -> 0 | J16: =COUNTIFS(底稿进度!B:B,看板!B16,底稿进度!M:M,"Y") -> 0 | K16: =COUNTIFS(底稿进度!B:B,看板!B16,底稿进度!N:N,"Y") -> 0 | L16: =COUNTIFS(底稿进度!B:B,看板!B16,底稿进度!S:S,"Y") -> 0 | M16: =COUNTIFS(底稿进度!B:B,看板!B16,底稿进度!T:T,"Y") -> 0 | N16: =COUNTIFS(底稿进度!B:B,看板!B16,底稿进度!U:U,"Y") -> 0 | O16: =COUNTIFS(底稿进度!B:B,看板!B16,底稿进度!V:V,"Y") -> 0 | P16: =COUNTIFS(底稿进度!B:B,看板!B16,底稿进度!W:W,"Y") -> 0 | Q16: =IF((_xlfn.XLOOKUP(B16,项目基础信息!B:B,项目基础信息!G:G)-$C$2)<0,"不适用",(_xlfn.XLOOKUP(B16,项目基础信息!B:B,项目基础信息!G:G)-$C$2)) -> 15
B21: 合计 | D21: =SUM(D5:D20) -> 6316.83 | E21: =SUM(E5:E20) -> 4751 | F21: =SUM(F5:F20) -> 1565.83 | G21: =SUM(G5:G20) -> 239 | H21: =SUM(H5:H20) -> 235 | I21: =SUM(I5:I20) -> 93 | J21: =SUM(J5:J20) -> 41 | K21: =SUM(K5:K20) -> 195 | ... P21: =SUM(P5:P20) -> 235
B24: 员工维度
B25: Preparer | C25: =G4 -> 底稿数量 | D25: =H4 -> BKD | E25: =I4 -> TOD | F25: cut off | G25: =K4 -> 其他程序 | H25: =L4 -> 已完成 | I25: FIC已复核 | J25: EIC已复核 | K25: =O4 -> 首次交付 | L25: =P4 -> 最终交付
B26: lucine lou | C26: =COUNTIFS(底稿进度!J:J,看板!B26) -> 56 | D26: =COUNTIFS(底稿进度!K:K,"Y",底稿进度!J:J,看板!B26) -> 55 | E26: =COUNTIFS(底稿进度!L:L,"Y",底稿进度!J:J,看板!B26) -> 4 | F26: =COUNTIFS(底稿进度!M:M,"Y",底稿进度!J:J,看板!B26) -> 7 | G26: =COUNTIFS(底稿进度!N:N,"Y",底稿进度!J:J,看板!B26) -> 32 | H26: =COUNTIFS(底稿进度!S:S,"Y",底稿进度!J:J,看板!B26) -> 55 | I26: =COUNTIFS(底稿进度!T:T,"Y",底稿进度!J:J,看板!B26) -> 55 | J26: =COUNTIFS(底稿进度!U:U,"Y",底稿进度!J:J,看板!B26) -> 55 | K26: =COUNTIFS(底稿进度!V:V,"Y",底稿进度!J:J,看板!B26) -> 55 | L26: =COUNTIFS(底稿进度!W:W,"Y",底稿进度!J:J,看板!B26) -> 55
B27: mengqi mq xu | C27: =COUNTIFS(底稿进度!J:J,看板!B27) -> 129 | D27: =COUNTIFS(底稿进度!K:K,"Y",底稿进度!J:J,看板!B27) -> 127 | E27: =COUNTIFS(底稿进度!L:L,"Y",底稿进度!J:J,看板!B27) -> 73 | F27: =COUNTIFS(底稿进度!M:M,"Y",底稿进度!J:J,看板!B27) -> 34 | G27: =COUNTIFS(底稿进度!N:N,"Y",底稿进度!J:J,看板!B27) -> 112 | H27: =COUNTIFS(底稿进度!S:S,"Y",底稿进度!J:J,看板!B27) -> 127 | I27: =COUNTIFS(底稿进度!T:T,"Y",底稿进度!J:J,看板!B27) -> 127 | J27: =COUNTIFS(底稿进度!U:U,"Y",底稿进度!J:J,看板!B27) -> 127 | K27: =COUNTIFS(底稿进度!V:V,"Y",底稿进度!J:J,看板!B27) -> 127 | L27: =COUNTIFS(底稿进度!W:W,"Y",底稿进度!J:J,看板!B27) -> 127
B28: taffy tian | C28: =COUNTIFS(底稿进度!J:J,看板!B28) -> 10 | D28: =COUNTIFS(底稿进度!K:K,"Y",底稿进度!J:J,看板!B28) -> 10 | E28: =COUNTIFS(底稿进度!L:L,"Y",底稿进度!J:J,看板!B28) -> 0 | F28: =COUNTIFS(底稿进度!M:M,"Y",底稿进度!J:J,看板!B28) -> 0 | G28: =COUNTIFS(底稿进度!N:N,"Y",底稿进度!J:J,看板!B28) -> 8 | H28: =COUNTIFS(底稿进度!S:S,"Y",底稿进度!J:J,看板!B28) -> 10 | I28: =COUNTIFS(底稿进度!T:T,"Y",底稿进度!J:J,看板!B28) -> 10 | J28: =COUNTIFS(底稿进度!U:U,"Y",底稿进度!J:J,看板!B28) -> 10 | K28: =COUNTIFS(底稿进度!V:V,"Y",底稿进度!J:J,看板!B28) -> 10 | L28: =COUNTIFS(底稿进度!W:W,"Y",底稿进度!J:J,看板!B28) -> 10
B29: hong yuan li | C29: =COUNTIFS(底稿进度!J:J,看板!B29) -> 17 | D29: =COUNTIFS(底稿进度!K:K,"Y",底稿进度!J:J,看板!B29) -> 17 | E29: =COUNTIFS(底稿进度!L:L,"Y",底稿进度!J:J,看板!B29) -> 15 | F29: =COUNTIFS(底稿进度!M:M,"Y",底稿进度!J:J,看板!B29) -> 0 | G29: =COUNTIFS(底稿进度!N:N,"Y",底稿进度!J:J,看板!B29) -> 17 | H29: =COUNTIFS(底稿进度!S:S,"Y",底稿进度!J:J,看板!B29) -> 17 | I29: =COUNTIFS(底稿进度!T:T,"Y",底稿进度!J:J,看板!B29) -> 17 | J29: =COUNTIFS(底稿进度!U:U,"Y",底稿进度!J:J,看板!B29) -> 17 | K29: =COUNTIFS(底稿进度!V:V,"Y",底稿进度!J:J,看板!B29) -> 17 | L29: =COUNTIFS(底稿进度!W:W,"Y",底稿进度!J:J,看板!B29) -> 17
B30: ting ting t wang | C30: =COUNTIFS(底稿进度!J:J,看板!B30) -> 2 | D30: =COUNTIFS(底稿进度!K:K,"Y",底稿进度!J:J,看板!B30) -> 2 | E30: =COUNTIFS(底稿进度!L:L,"Y",底稿进度!J:J,看板!B30) -> 0 | F30: =COUNTIFS(底稿进度!M:M,"Y",底稿进度!J:J,看板!B30) -> 0 | G30: =COUNTIFS(底稿进度!N:N,"Y",底稿进度!J:J,看板!B30) -> 2 | H30: =COUNTIFS(底稿进度!S:S,"Y",底稿进度!J:J,看板!B30) -> 2 | I30: =COUNTIFS(底稿进度!T:T,"Y",底稿进度!J:J,看板!B30) -> 2 | J30: =COUNTIFS(底稿进度!U:U,"Y",底稿进度!J:J,看板!B30) -> 2 | K30: =COUNTIFS(底稿进度!V:V,"Y",底稿进度!J:J,看板!B30) -> 2 | L30: =COUNTIFS(底稿进度!W:W,"Y",底稿进度!J:J,看板!B30) -> 2
B31: sissi xx liu | C31: =COUNTIFS(底稿进度!J:J,看板!B31) -> 19 | D31: =COUNTIFS(底稿进度!K:K,"Y",底稿进度!J:J,看板!B31) -> 19 | E31: =COUNTIFS(底稿进度!L:L,"Y",底稿进度!J:J,看板!B31) -> 0 | F31: =COUNTIFS(底稿进度!M:M,"Y",底稿进度!J:J,看板!B31) -> 0 | G31: =COUNTIFS(底稿进度!N:N,"Y",底稿进度!J:J,看板!B31) -> 19 | H31: =COUNTIFS(底稿进度!S:S,"Y",底稿进度!J:J,看板!B31) -> 19 | I31: =COUNTIFS(底稿进度!T:T,"Y",底稿进度!J:J,看板!B31) -> 19 | J31: =COUNTIFS(底稿进度!U:U,"Y",底稿进度!J:J,看板!B31) -> 19 | K31: =COUNTIFS(底稿进度!V:V,"Y",底稿进度!J:J,看板!B31) -> 19 | L31: =COUNTIFS(底稿进度!W:W,"Y",底稿进度!J:J,看板!B31) -> 19
B32: kyon cui | C32: =COUNTIFS(底稿进度!J:J,看板!B32) -> 5 | D32: =COUNTIFS(底稿进度!K:K,"Y",底稿进度!J:J,看板!B32) -> 5 | E32: =COUNTIFS(底稿进度!L:L,"Y",底稿进度!J:J,看板!B32) -> 1 | F32: =COUNTIFS(底稿进度!M:M,"Y",底稿进度!J:J,看板!B32) -> 0 | G32: =COUNTIFS(底稿进度!N:N,"Y",底稿进度!J:J,看板!B32) -> 5 | H32: =COUNTIFS(底稿进度!S:S,"Y",底稿进度!J:J,看板!B32) -> 5 | I32: =COUNTIFS(底稿进度!T:T,"Y",底稿进度!J:J,看板!B32) -> 5 | J32: =COUNTIFS(底稿进度!U:U,"Y",底稿进度!J:J,看板!B32) -> 5 | K32: =COUNTIFS(底稿进度!V:V,"Y",底稿进度!J:J,看板!B32) -> 5 | L32: =COUNTIFS(底稿进度!W:W,"Y",底稿进度!J:J,看板!B32) -> 5
B33: jane q wang | C33: =COUNTIFS(底稿进度!J:J,看板!B33) -> 1 | D33: =COUNTIFS(底稿进度!K:K,"Y",底稿进度!J:J,看板!B33) -> 0 | E33: =COUNTIFS(底稿进度!L:L,"Y",底稿进度!J:J,看板!B33) -> 0 | F33: =COUNTIFS(底稿进度!M:M,"Y",底稿进度!J:J,看板!B33) -> 0 | G33: =COUNTIFS(底稿进度!N:N,"Y",底稿进度!J:J,看板!B33) -> 0 | H33: =COUNTIFS(底稿进度!S:S,"Y",底稿进度!J:J,看板!B33) -> 0 | I33: =COUNTIFS(底稿进度!T:T,"Y",底稿进度!J:J,看板!B33) -> 0 | J33: =COUNTIFS(底稿进度!U:U,"Y",底稿进度!J:J,看板!B33) -> 0 | K33: =COUNTIFS(底稿进度!V:V,"Y",底稿进度!J:J,看板!B33) -> 0 | L33: =COUNTIFS(底稿进度!W:W,"Y",底稿进度!J:J,看板!B33) -> 0
C34: =COUNTIFS(底稿进度!J:J,看板!B34) -> 0 | D34: =COUNTIFS(底稿进度!K:K,"Y",底稿进度!J:J,看板!B34) -> 0 | E34: =COUNTIFS(底稿进度!L:L,"Y",底稿进度!J:J,看板!B34) -> 0 | F34: =COUNTIFS(底稿进度!M:M,"Y",底稿进度!J:J,看板!B34) -> 0 | G34: =COUNTIFS(底稿进度!N:N,"Y",底稿进度!J:J,看板!B34) -> 0 | H34: =COUNTIFS(底稿进度!S:S,"Y",底稿进度!J:J,看板!B34) -> 0 | I34: =COUNTIFS(底稿进度!T:T,"Y",底稿进度!J:J,看板!B34) -> 0 | J34: =COUNTIFS(底稿进度!U:U,"Y",底稿进度!J:J,看板!B34) -> 0 | K34: =COUNTIFS(底稿进度!V:V,"Y",底稿进度!J:J,看板!B34) -> 0 | L34: =COUNTIFS(底稿进度!W:W,"Y",底稿进度!J:J,看板!B34) -> 0
C35: =COUNTIFS(底稿进度!J:J,看板!B35) -> 0 | D35: =COUNTIFS(底稿进度!K:K,"Y",底稿进度!J:J,看板!B35) -> 0 | E35: =COUNTIFS(底稿进度!L:L,"Y",底稿进度!J:J,看板!B35) -> 0 | F35: =COUNTIFS(底稿进度!M:M,"Y",底稿进度!J:J,看板!B35) -> 0 | G35: =COUNTIFS(底稿进度!N:N,"Y",底稿进度!J:J,看板!B35) -> 0 | H35: =COUNTIFS(底稿进度!S:S,"Y",底稿进度!J:J,看板!B35) -> 0 | I35: =COUNTIFS(底稿进度!T:T,"Y",底稿进度!J:J,看板!B35) -> 0 | J35: =COUNTIFS(底稿进度!U:U,"Y",底稿进度!J:J,看板!B35) -> 0 | K35: =COUNTIFS(底稿进度!V:V,"Y",底稿进度!J:J,看板!B35) -> 0 | L35: =COUNTIFS(底稿进度!W:W,"Y",底稿进度!J:J,看板!B35) -> 0
B36: 合计 | C36: =SUM(C26:C35) -> 239 | D36: =SUM(D26:D35) -> 235 | E36: =SUM(E26:E35) -> 93 | G36: =SUM(G26:G35) -> 195 | H36: =SUM(H26:H35) -> 235 | J36: =SUM(J26:J35) -> 235 | K36: =SUM(K26:K35) -> 235 | L36: =SUM(L26:L35) -> 235
C37: =C36-G21 -> 0

Sheet 项目基础信息
B2: 服务单号 | C2: 项目名称 | D2: 项目类型 | E2: 项目类型 | F2: section | G2: 首次交付DDL | H2: 整体交付DDL | I2: 报告日 | J2: 交付时间备注 | K2: 项目组SP | L2: 公盘link | M2: 沟通方式 | N2: 项目组EIC | O2: 项目组FIC | P2: 备注
B3: 47115251- EDC251017001 | C3: 瑞云冷链 | E3: =_xlfn.XLOOKUP(B3,'[1]SG原始数据（每周一更新）'!$F:$F,'[1]SG原始数据（每周一更新）'!$T:$T) -> IPO | F3: C+函证（含CSP01/02) | G3: 46127 | H3: 46132 | I3: 46142 | J3: 4/15首次交付；4/20最终交付 | K3: OneDrive | L3: 无 | M3: 直接对接客户，微信群联系Allen | N3: lexi.lv | O3: Nicole J Chen
B4: 47035622- EDC250625001 | C4: PAOB | E4: =_xlfn.XLOOKUP(B4,'[1]SG原始数据（每周一更新）'!$F:$F,'[1]SG原始数据（每周一更新）'!$T:$T) -> FSO PIE | F4: C/K1/L2/N/Q1/Uexp及非标 | G4: 46087 | H4: 46098 | I4: 46104 | J4: 2.13前交付部分底稿 | K4: Pao Bank - FY2025 - Documents - Database - All Documents | L4: 无 | M4: 不直接对接客户 | N4: Samuel.Chow | O4: Allen
B5: 47096395- EDC250620001 | C5: 香奈儿 | E5: =_xlfn.XLOOKUP(B5,'[1]SG原始数据（每周一更新）'!$F:$F,'[1]SG原始数据（每周一更新）'!$T:$T) -> MNC | F5: C+函证/Uexp/N以及ENGP及费用other的BKD | G5: 46086 | H5: 46094 | I5: 46158 | J5: 2.27前分批交付 | K5: EY-CHANEL - 文档 - 所有文档 | L5: 无 | M5: 不直接对接客户 | N5: Allen.Ai | O5: Arthur C Zhang;Mia Cao
B6: 47095110- EDC250620001 | C6: DNE | E6: =_xlfn.XLOOKUP(B6,'[1]SG原始数据（每周一更新）'!$F:$F,'[1]SG原始数据（每周一更新）'!$T:$T) -> Non-PIE | F6: C+函证（含CSP02）/Q/Uexp/Skywind上数 | G6: 46101 | H6: 46112 | I6: 46157 | J6: 2.9前分批交付，优先Q | K6: DNE - 2025 DNE - 所有文档 | L6: \\Cnshausrfl110\110shu00033\D\DJNewEaseG_AUD2023-12DJNewEaseGroup\【DNE 2025】 | M6: 邮件沟通 | N6: joanne.ni1,rose.qi | O6: Jocelyn Qin
B7: 47095951- EDC250620001 | C7: 江苏瑞科 | E7: =_xlfn.XLOOKUP(B7,'[1]SG原始数据（每周一更新）'!$F:$F,'[1]SG原始数据（每周一更新）'!$T:$T) -> PIE | F7: C+函证/K1/L1/Q | G7: 46085 | H7: 46094 | I7: 46109 | J7: 2.15前首次交付定数，2.27整体交付 | K7: 江苏瑞科Recbio - Documents - Recbio_20250930_预审 - All Documents | L7: \\Cnshausrfl110.ey.net\110shu00044\J\Jia_4163656_Jiangsu Rec Biotechnology | M7: 直接对接客户，微信群 | N7: wesley.pei | O7: Mia MX Yuan
B8: 47095577- EDC250530001 | C8: H3C | E8: =_xlfn.XLOOKUP(B8,'[1]SG原始数据（每周一更新）'!$F:$F,'[1]SG原始数据（每周一更新）'!$T:$T) -> PIE | F8: C+函证/J/K1/L1/N/Q | G8: 46101 | H8: 46111 | I8: 46141 | J8: 2.6-2.13分批交付，2.13定数 | K8: H3C_2022 - Documents - 2025 1231 - All Documents | L8: 通过客户PBC系统要资料 | M8: 不直接对接客户 | N8: donald.gu | O8: Chris CX Wang
B9: 47094516- EDC250620002 | C9: 瀚瑞森 | E9: =_xlfn.XLOOKUP(B9,'[1]SG原始数据（每周一更新）'!$F:$F,'[1]SG原始数据（每周一更新）'!$T:$T) -> MNC | F9: C+函证/K1/Q | G9: 46129 | H9: 46133 | I9: 46171 | J9: 4月份年审 | K9: 看板 - 安永中国客户交互平台 | L9: 无SP和公盘，通过CCP要资料 | M9: 不直接对接客户 | N9: tina.ren | O9: Ryan.jy.ruan 联系harry.hj.yan
B10: 47097374- EDC250613002 | C10: 乐尔幸 | E10: =_xlfn.XLOOKUP(B10,'[1]SG原始数据（每周一更新）'!$F:$F,'[1]SG原始数据（每周一更新）'!$T:$T) -> MNC | F10: C+函证/K1/L1/N/Uexp及费用other | G10: 46092 | H10: 46098 | I10: 46142 | J10: 2月初交付C底稿，3.14交付其他 | K10: 无 | L10: \\Cnshausrfl120.ey.net\120shu05025\D\Don_4526624_AUD2021-12 Dongguan Solum\Pantos\2025 | M10: 直接对接客户，广州发给 <cathy.liu@lxpantos.com>、<amy.zhang@lxpantos.com>抄送 <yongsoo.park@lxpantos.com>、<Terry.ZL.Wang@cn.ey.com>、<Yana.Yin@cn.ey.com>；深圳发给发给 <clare.chen@lxpantos.com>抄送 <yongsoo.park@lxpantos.com>、<Terry.ZL.Wang@cn.ey.com>、<Yana.Yin@cn.ey.com> | N10: Terry.ZL.Wang,Catherine-C.Zhang | O10: Yana Yin
B11: 47095936- EDC260401002 | C11: 李尔汽车部件 | E11: =_xlfn.XLOOKUP(B11,'[1]SG原始数据（每周一更新）'!$F:$F,'[1]SG原始数据（每周一更新）'!$T:$T) -> MNC | F11: J/K/L1 | G11: 46136 | H11: 46142 | I11: 46189 | J11: 4/17交付 | K11: OneDrive | L11: 无 | M11: 不直接对接客户 | N11: kyle.lou | O11: 对接人Wang Han Wu
B12: 47095226- EDC260403001 | C12: 李尔中国投资 | E12: =_xlfn.XLOOKUP(B12,'[1]SG原始数据（每周一更新）'!$F:$F,'[1]SG原始数据（每周一更新）'!$T:$T) -> MNC | F12: J/K/L1/L2 | G12: 46136 | H12: 46142 | I12: 46171 | J12: 4/17交付 | K12: OneDrive | L12: 无 | M12: 不直接对接客户 | N12: Jackie.HJ.Ma,Zoe-Q.Zhang | O12: 对接人Sune Wang
B13: 47076663- EDC260119001 | C13: 紫光展锐 | E13: =_xlfn.XLOOKUP(B13,'[1]SG原始数据（每周一更新）'!$F:$F,'[1]SG原始数据（每周一更新）'!$T:$T) -> IPO | F13: C/K/L1/L2/Uexp销管财 | G13: 46164 | H13: 46189 | I13: 46203 | J13: 最晚5月底交 | K13: 无 | L13: //cnshausrfl110/110shu00013/U/UnisocShan_UnisocIPO/ | M13: 不直接对接客户 | N13: Rick RW Wang | O13: FIC：Tallen Zhao 对接人Kevin HJ Zhou、Sienna JN Zhou
B14: 47137340- EDC260527002 | C14: 万帮数字 | E14: =_xlfn.XLOOKUP(B14,'[1]SG原始数据（每周一更新）'!$F:$F,'[1]SG原始数据（每周一更新）'!$T:$T) -> IPO | F14: K/Q/Uexp VC&VD/ Uexp Others | G14: 46191 | H14: 46213 | I14: 46234 | J14: 6.18首次交付Q/Uexp Others；6.26首次交付K1/Uexp VC&VD | K14: benu_2026 - Documents - 所有文档 | L14: 无 | M14: 飞书对接客户，主要是项目组 | N14: Jane ZH Liu | O14: Rocky L Yu
B18: 紫光展锐
B19: CRA路径：\\Cnshausrfl110\110shu00013\U\UnisocShan_UnisocIPO\3. WP\2025年\
B20: 20251231PBC路径：\\Cnshausrfl110\110shu00013\U\UnisocShan_UnisocIPO\1. PBC\8. 2025年资料\20251231\
B21: WP路径：\\Cnshausrfl110\110shu00013\U\UnisocShan_UnisocIPO\3. WP\0. For EIC Review\20251231\Kevin Zhou\
B22: 长期资产PBC路径：\\Cnshausrfl110\110shu00013\U\UnisocShan_UnisocIPO\1. PBC\8. 2025年资料\20251231\44.recon更新\
B23: 期后JE：\\Cnshausrfl110\110shu00013\U\UnisocShan_UnisocIPO\1. PBC\8. 2025年资料\20251231\97.期后26年1月报表、余额表、序时账\
B24: 以前年度底稿：\\Cnshausrfl110\110shu00013\U\UnisocShan_UnisocIPO\3. WP\0. For EIC Review\OLD
B25: 最新报表路径请看v34，和GET数据是一样的，就是形式上是报表形式：\\Cnshausrfl110\110shu00013\U\UnisocShan_UnisocIPO\1. PBC\1. 报表&JE&TB&调整底稿\报表\2025年\20251231\
B26: 最新报表附注请看v7：\\Cnshausrfl110\110shu00013\U\UnisocShan_UnisocIPO\1. PBC\8. 2025年资料\20251231\0.合并附注\展锐IPO 2025年附注 V7版\
B29: 难点卡点写在下面：
B30: 香奈儿：主要在沟通成本较高/梳理取数逻辑
B31: 1.客户提供的PBC与常规项目不同，同事在寻找和应用PBC时有困难，得需要跟项目组沟通。
... B34: 4.部分科目需要列示PRC和ifrs两个口径的BKD，我们对ifrs口径的逻辑关系不熟悉，需要花时间梳理

Sheet 银行函证进度
B1: 每天打开函证网站关注待办事项，尤其是未决及异常事项；涉及地址核查的及时关注核查结果；每周三、周五在下表中更新函证进度
B2: 服务单号 | C2: 项目 | D2: 第14项 | E2: 收集表 | F2: 电子格式一 | G2: 电子格式二 | H2: 纸质格式一 | I2: 纸质格式二 | J2: HK17 | K2: confirmation | L2: 合计生成 | M2: 已发出 | N2: 未发出 | O2: 已收回 | P2: 未收回 | Q2: 备注 | R2: 负责人
B3: 47115251- EDC251017001 | C3: 瑞云冷链-2324 | D3: 授信及其他 | E3: 客户填写EDC整理 | F3: 57 | G3: 14 | H3: 128 | I3: 9 | J3: 0 | K3: 0 | L3: =SUM(F3:K3) -> 208 | M3: =L3-N3 -> 208 | N3: 0 | O3: 208 | P3: =M3-O3 -> 0 | R3: mengqi | S3: =M3-O3-P3 -> 0
B4: 47115251- EDC251017001 | C4: 瑞云冷链-2025 | D4: 授信及其他 | E4: 客户填写EDC整理 | F4: 44 | G4: 13 | H4: 113 | I4: 8 | J4: 3 | K4: 0 | L4: =SUM(F4:K4) -> 181 | M4: 181 | N4: 0 | O4: 181 | P4: =M4-O4 -> 0 | R4: mengqi | S4: =M4-O4-P4 -> 0
B5: 47096395- EDC250620001 | C5: 香奈儿 | D5: 不函 | E5: EDC根据上年整理 | F5: 0 | G5: 34 | H5: 3 | I5: 0 | J5: 0 | K5: 0 | L5: =SUM(F5:K5) -> 37 | M5: =L5-N5 -> 37 | N5: 0 | O5: 37 | P5: 0 | R5: mengqi | S5: =M5-O5-P5 -> 0
B6: 47095110- EDC250620001 | C6: DNE | D6: 仅已签订合同但尚未提供资金的贷款 | E6: EDC根据余额大表及融资台账等整理 | F6: 1 | G6: 0 | H6: =163+1+2-1 -> 165 | I6: =241+12+3 -> 256 | J6: =109+6 -> 115 | K6: 0 | L6: =SUM(F6:K6) -> 537 | M6: =L6-N6 -> 537 | N6: 0 | O6: 537 | P6: =M6-O6 -> 0 | R6: lucine | S6: =M6-O6-P6 -> 0
B7: 47095951- EDC250620001 | C7: 江苏瑞科 | D7: 授信及其他 | E7: 客户填写2.0模板 | F7: 5 | G7: 10 | H7: 7 | I7: 0 | J7: 2 | K7: 0 | L7: =SUM(F7:K7) -> 24 | M7: =L7-N7 -> 24 | N7: 0 | O7: 24 | P7: 0 | R7: mengqi | S7: =M7-O7-P7 -> 0
B8: 47095577- EDC250530001 | C8: H3C | D8: 不函 | E8: 项目组填写 | F8: 0 | G8: 29 | H8: 7 | I8: 60 | J8: 4 | K8: 2 | L8: =SUM(F8:K8) -> 102 | M8: 102 | N8: 0 | O8: 101 | P8: 1 | Q8: 工行澳门不回做替代 | R8: mengqi | S8: =M8-O8-P8 -> 0
B9: 47094516- EDC250620002 | C9: 瀚瑞森 | D9: 已签订合同但尚未提供资金的贷款（无） | E9: 客户填写2.0模板 | F9: 0 | G9: 1 | H9: 1 | I9: 0 | J9: 0 | K9: 0 | L9: =SUM(F9:K9) -> 2 | M9: =L9-N9 -> 2 | N9: 0 | O9: 2 | P9: 0 | R9: lucine | S9: =M9-O9-P9 -> 0
B10: 47097374- EDC250613002 | C10: 乐尔幸 | D10: 授信及其他 | E10: 客户填写2.0模板 | F10: 0 | G10: 0 | H10: 6 | I10: 0 | J10: 0 | K10: 0 | L10: =SUM(F10:K10) -> 6 | M10: =L10-N10 -> 6 | N10: 0 | O10: 6 | P10: =M10-O10 -> 0 | R10: lucine | S10: =M10-O10-P10 -> 0
E11: 合计 | F11: =SUM(F3:F10) -> 107 | G11: =SUM(G3:G10) -> 101 | H11: =SUM(H3:H10) -> 430 | I11: =SUM(I3:I10) -> 333 | J11: =SUM(J3:J10) -> 124 | K11: =SUM(K3:K10) -> 2 | L11: =SUM(L3:L10) -> 1097 | M11: =SUM(M3:M10) -> 1097 | ... P11: =SUM(P3:P10) -> 1 | Q11: =L11-M11-N11 -> 0

Sheet 底稿进度
B1: 每日更新下表底稿进度，下班前口头跟FIC沟通下完成情况及卡点；已完成底稿提前FIC复核前需根据checklist自查
B2: WP服务单 | C2: 项目 | D2: entity | E2: section | F2: 底稿年份 | G2: 列示方式 | H2: 程序 | I2: Pre DDL | J2: 负责人 | K2: BKD | L2: TOD | M2: cut off | N2: 其他程序 | O2: OS事项 | P2: 事项分类 | Q2: 备注 | R2: 是否自查 | S2: 是否完成 | T2: FIC复核 | U2: EIC复核 | V2: 首次交付 | W2: 最终交付
B3: 47096395- EDC250620001 | C3: 香奈儿 | D3: 香奈儿（中国）贸易有限公司 | E3: C_货币资金 | F3: 2025/12/31 | G3: 单体 | H3: 所有PSP | I3: 46068 | J3: lucine lou | K3: Y | L3: N/A | M3: Y | N3: Y | O3: 无 | P3: 无 | Q3: 无 | R3: Y | S3: Y | T3: Y | U3: Y | V3: Y | W3: Y
B4: 47096395- EDC250620001 | C4: 香奈儿 | D4: 香奈儿（中国）贸易有限公司 | E4: E1_应收账款 | F4: 2025/12/31 | G4: 单体 | H4: 只做BKD | I4: 46068 | J4: lucine lou | K4: Y | L4: N/A | M4: N/A | N4: N/A | O4: 无 | P4: 无 | Q4: 无 | R4: Y | S4: Y | T4: Y | U4: Y | V4: Y | W4: Y
B5: 47096395- EDC250620001 | C5: 香奈儿 | D5: 香奈儿（中国）贸易有限公司 | E5: G1_流动资产类科目(不含G3预付账款） | F5: 2025/12/31 | G5: 单体 | H5: 只做BKD | I5: 46068 | J5: lucine lou | K5: Y | L5: N/A | M5: N/A | N5: N/A | O5: 无 | P5: 无 | Q5: 无 | R5: Y | S5: Y | T5: Y | U5: Y | V5: Y | W5: Y
B6: 47096395- EDC250620001 | C6: 香奈儿 | D6: 香奈儿（中国）贸易有限公司 | E6: G2_长期应收款 | F6: 2025/12/31 | G6: 单体 | H6: 只做BKD | I6: 46068 | J6: lucine lou | K6: Y | L6: N/A | M6: N/A | N6: N/A | O6: 无 | P6: 无 | Q6: 无 | R6: Y | S6: Y | T6: Y | U6: Y | V6: Y | W6: Y
B7: 47096395- EDC250620001 | C7: 香奈儿 | D7: 香奈儿（中国）贸易有限公司 | E7: G3_预付账款及待摊费用 | F7: 2025/12/31 | G7: 单体 | H7: 只做BKD | I7: 46068 | J7: lucine lou | K7: Y | L7: N/A | M7: N/A | N7: N/A | O7: 无 | P7: 无 | Q7: 无 | R7: Y | S7: Y | T7: Y | U7: Y | V7: Y | W7: Y
B8: 47096395- EDC250620001 | C8: 香奈儿 | D8: 香奈儿（中国）贸易有限公司 | E8: P1_流动负债类科目 | F8: 2025/12/31 | G8: 单体 | H8: 只做BKD | I8: 46077 | J8: mengqi mq xu | K8: Y | L8: N/A | M8: N/A | N8: N/A | O8: 无 | P8: 无 | Q8: 无 | R8: Y | S8: Y | T8: Y | U8: Y | V8: Y | W8: Y
B9: 47096395- EDC250620001 | C9: 香奈儿 | D9: 香奈儿（中国）贸易有限公司 | E9: P3_合同负债及预收账款 | F9: 2025/12/31 | G9: 单体 | H9: 只做BKD | I9: 46068 | J9: lucine lou | K9: Y | L9: N/A | M9: N/A | N9: N/A | O9: 无 | P9: 无 | Q9: 无 | R9: Y | S9: Y | T9: Y | U9: Y | V9: Y | W9: Y
B10: 47096395- EDC250620001 | C10: 香奈儿 | D10: 香奈儿（中国）贸易有限公司 | E10: P5_长期应付款及其他非流动负债 | F10: 2025/12/31 | G10: 单体 | H10: 只做BKD | I10: 46068 | J10: mengqi mq xu | K10: Y | L10: N/A | M10: N/A | N10: N/A | O10: 无 | P10: 无 | Q10: 无 | R10: Y | S10: Y | T10: Y | U10: Y | V10: Y | W10: Y
B11: 47096395- EDC250620001 | C11: 香奈儿 | D11: 香奈儿（中国）贸易有限公司 | E11: U_exp_other | F11: 2025/12/31 | G11: 单体 | H11: 只做BKD | I11: 46068 | J11: lucine lou | K11: Y | L11: N/A | M11: N/A | N11: N/A | O11: 无 | P11: 无 | Q11: 无 | R11: Y | S11: Y | T11: Y | U11: Y | V11: Y | W11: Y
B12: 47096395- EDC250620001 | C12: 香奈儿 | D12: 香奈儿（中国）贸易有限公司 | E12: U_exp_VC&VD | F12: 2025/12/31 | G12: 单体 | H12: 只做BKD | I12: 46068 | J12: mengqi mq xu | K12: Y | L12: N/A | M12: N/A | N12: N/A | O12: 无 | P12: 无 | Q12: 无 | R12: Y | S12: Y | T12: Y | U12: Y | V12: Y | W12: Y
B13: 47096395- EDC250620001 | C13: 香奈儿 | D13: 香奈儿（中国）贸易有限公司 | E13: N_应付账款 | F13: 2025/12/31 | G13: 单体 | H13: 只做BKD | I13: 46068 | J13: lucine lou | K13: Y | L13: N/A | M13: N/A | N13: N/A | O13: 无 | P13: 无 | Q13: 无 | R13: Y | S13: Y | T13: Y | U13: Y | V13: Y | W13: Y
B14: 47095951- EDC250620001 | C14: 江苏瑞科 | D14: 江苏瑞科生物技术股份有限公司 | E14: C_货币资金 | F14: 2025/12/31 | G14: 单体 | H14: 所有PSP | I14: 46052 | J14: mengqi mq xu | K14: Y | L14: N/A | M14: Y | N14: Y | O14: 无 | P14: 无 | Q14: 无 | R14: Y | S14: Y | T14: Y | U14: Y | V14: Y | W14: Y
... B190: 47076663- EDC260119001 | C190: 紫光展锐 | D190: 紫光展锐（上海）科技股份有限公司 | E190: C_货币资金 | F190: 2025/12/31 | G190: 合并 | H190: 所有PSP | I190: 46157 | J190: lucine lou | K190: Y | L190: N/A | M190: Y | N190: Y | O190: 无 | P190: 无 | Q190: 无 | R190: Y | S190: Y | T190: Y | U190: Y | V190: Y | W190: Y
B191: 47076663- EDC260119001 | C191: 紫光展锐 | D191: 展讯通信（上海）有限公司 | E191: K1_固定资产 | F191: 2025/12/31 | G191: 单体 | H191: 所有PSP | I191: 46157 | J191: mengqi mq xu | K191: Y | L191: Y | M191: N/A | N191: Y | O191: 改扩建折旧方法存在问题，OS交付 | P191: 提醒事项：待项目组跟进 | Q191: 无 | R191: Y | S191: Y | T191: Y | U191: Y | V191: Y | W191: Y | X191: 3000
B192: 47076663- EDC260119001 | C192: 紫光展锐 | D192: 展讯通信（天津）有限公司 | E192: K1_固定资产 | F192: 2025/12/31 | G192: 单体 | H192: 所有PSP | I192: 46157 | J192: hong yuan li | K192: Y | L192: N/A | M192: N/A | N192: Y | O192: 无 | P192: 无 | Q192: 无 | R192: Y | S192: Y | T192: Y | U192: Y | V192: Y | W192: Y | X192: 3300
B193: 47076663- EDC260119001 | C193: 紫光展锐 | D193: 北京紫光展锐通信技术有限公司 | E193: K1_固定资产 | F193: 2025/12/31 | G193: 单体 | H193: 所有PSP | I193: 46157 | J193: hong yuan li | K193: Y | L193: N/A | M193: N/A | N193: Y | O193: 无 | P193: 无 | Q193: 无 | R193: Y | S193: Y | T193: Y | U193: Y | V193: Y | W193: Y | X193: 4000
B194: 47076663- EDC260119001 | C194: 紫光展锐 | D194: 展讯通信（深圳）有限公司 | E194: K1_固定资产 | F194: 2025/12/31 | G194: 单体 | H194: 所有PSP | I194: 46157 | J194: mengqi mq xu | K194: Y | L194: N/A | M194: N/A | N194: Y | O194: 无 | P194: 无 | Q194: 无 | R194: Y | S194: Y | T194: Y | U194: Y | V194: Y | W194: Y | X194: 7400
B195: 47076663- EDC260119001 | C195: 紫光展锐 | D195: Spreadtrum Communications USA Inc. | E195: K1_固定资产 | F195: 2025/12/31 | G195: 单体 | H195: 所有PSP | I195: 46157 | J195: mengqi mq xu | K195: Y | L195: 已抽样 | M195: N/A | N195: Y | O195: TOD资料尚未提供 | P195: OS_PBC | Q195: 无 | R195: Y | S195: Y | T195: Y | U195: Y | V195: Y | W195: Y | X195: 2100
B196: 47076663- EDC260119001 | C196: 紫光展锐 | D196: 西安紫光展锐科技有限公司 | E196: K1_固定资产 | F196: 2025/12/31 | G196: 单体 | H196: 所有PSP | I196: 46157 | J196: mengqi mq xu | K196: Y | L196: N/A | M196: N/A | N196: Y | O196: 无 | P196: 无 | Q196: 无 | R196: Y | S196: Y | T196: Y | U196: Y | V196: Y | W196: Y | X196: 1900
B197: 47076663- EDC260119001 | C197: 紫光展锐 | D197: 厦门紫光展锐科技有限公司 | E197: K1_固定资产 | F197: 2025/12/31 | G197: 单体 | H197: 所有PSP | I197: 46157 | J197: mengqi mq xu | K197: Y | L197: N/A | M197: N/A | N197: Y | O197: 无 | P197: 无 | Q197: 无 | R197: Y | S197: Y | T197: Y | U197: Y | V197: Y | W197: Y | X197: XMZR8900
B198: 47076663- EDC260119001 | C198: 紫光展锐 | D198: 锐迪科微电子（上海）有限公司 | E198: K1_固定资产 | F198: 2025/12/31 | G198: 单体 | H198: 所有PSP | I198: 46157 | J198: mengqi mq xu | K198: Y | L198: N/A | M198: N/A | N198: Y | O198: 无 | P198: 无 | Q198: 无 | R198: Y | S198: Y | T198: Y | U198: Y | V198: Y | W198: Y | X198: 4500
B199: 47076663- EDC260119001 | C199: 紫光展锐 | D199: 锐迪科微电子科技（上海）有限公司 | E199: K1_固定资产 | F199: 2025/12/31 | G199: 单体 | H199: 所有PSP | I199: 46157 | J199: mengqi mq xu | K199: Y | L199: Y | M199: N/A | N199: Y | O199: 无 | P199: 无 | Q199: 无 | R199: Y | S199: Y | T199: Y | U199: Y | V199: Y | W199: Y | X199: 4600
B200: 47076663- EDC260119001 | C200: 紫光展锐 | D200: RDA Technologies Limited | E200: K1_固定资产 | F200: 2025/12/31 | G200: 单体 | H200: 所有PSP | I200: 46151 | J200: lucine lou | K200: Y | L200: N/A | M200: N/A | N200: Y | O200: 无 | P200: 无 | Q200: 无 | R200: Y | S200: Y | T200: Y | U200: Y | V200: Y | W200: Y | X200: 4800
B201: 47076663- EDC260119001 | C201: 紫光展锐 | D201: 紫光展锐（上海）科技有限公司 | E201: K1_固定资产 | F201: 2025/12/31 | G201: 单体 | H201: 所有PSP | I201: 46151 | J201: mengqi mq xu | K201: Y | L201: N/A | M201: N/A | N201: Y | O201: 无 | P201: 无 | Q201: 无 | R201: Y | S201: Y | T201: Y | U201: Y | V201: Y | W201: Y | X201: 8700
B202: 47076663- EDC260119001 | C202: 紫光展锐 | D202: 展讯半导体（成都）有限公司 | E202: K1_固定资产 | F202: 2025/12/31 | G202: 单体 | H202: 所有PSP | I202: 46151 | J202: ting ting t wang | K202: Y | L202: N/A | M202: N/A | N202: Y | O202: 无 | P202: 无 | Q202: 无 | R202: Y | S202: Y | T202: Y | U202: Y | V202: Y | W202: Y | X202: 9200
B203: 47076663- EDC260119001 | C203: 紫光展锐 | D203: 紫光展锐（重庆）科技有限公司 | E203: K1_固定资产 | F203: 2025/12/31 | G203: 单体 | H203: 所有PSP | I203: 46151 | J203: ting ting t wang | K203: Y | L203: N/A | M203: N/A | N203: Y | O203: 无 | P203: 无 | Q203: 无 | R203: Y | S203: Y | T203: Y | U203: Y | V203: Y | W203: Y | X203: 1700
B204: 47076663- EDC260119001 | C204: 紫光展锐 | D204: 展讯通信（上海）有限公司 | E204: L2_长期待摊费用 | F204: 2025/12/31 | G204: 单体 | H204: 所有PSP | I204: 46151 | J204: sissi xx liu | K204: Y | L204: N/A | M204: N/A | N204: Y | O204: 无 | P204: 无 | Q204: 无 | R204: Y | S204: Y | T204: Y | U204: Y | V204: Y | W204: Y | X204: 3000
B205: 47076663- EDC260119001 | C205: 紫光展锐 | D205: 展讯通信（深圳）有限公司 | E205: L2_长期待摊费用 | F205: 2025/12/31 | G205: 单体 | H205: 所有PSP | I205: 46151 | J205: sissi xx liu | K205: Y | L205: N/A | M205: N/A | N205: Y | O205: 无 | P205: 无 | Q205: 无 | R205: Y | S205: Y | T205: Y | U205: Y | V205: Y | W205: Y | X205: 7400
B206: 47076663- EDC260119001 | C206: 紫光展锐 | D206: 紫光展锐（上海）科技有限公司 | E206: L2_长期待摊费用 | F206: 2025/12/31 | G206: 单体 | H206: 所有PSP | I206: 46151 | J206: sissi xx liu | K206: Y | L206: N/A | M206: N/A | N206: Y | O206: 无 | P206: 无 | Q206: 无 | R206: Y | S206: Y | T206: Y | U206: Y | V206: Y | W206: Y | X206: 8700
B207: 47076663- EDC260119001 | C207: 紫光展锐 | D207: 展讯通信（上海）有限公司 | E207: L1_无形资产 | F207: 2025/12/31 | G207: 单体 | H207: 所有PSP | I207: 46151 | J207: kyon cui | K207: Y | L207: Y | M207: N/A | N207: Y | O207: 无 | P207: 无 | Q207: 无 | R207: Y | S207: Y | T207: Y | U207: Y | V207: Y | W207: Y | X207: 3000
B208: 47076663- EDC260119001 | C208: 紫光展锐 | D208: 展讯通信（天津）有限公司 | E208: L1_无形资产 | F208: 2025/12/31 | G208: 单体 | H208: 所有PSP | I208: 46151 | J208: kyon cui | K208: Y | L208: N/A | M208: N/A | N208: Y | O208: 无 | P208: 无 | Q208: 无 | R208: Y | S208: Y | T208: Y | U208: Y | V208: Y | W208: Y | X208: 3300
B209: 47076663- EDC260119001 | C209: 紫光展锐 | D209: 展讯通信（深圳）有限公司 | E209: L1_无形资产 | F209: 2025/12/31 | G209: 单体 | H209: 所有PSP | I209: 46151 | J209: kyon cui | K209: Y | L209: N/A | M209: N/A | N209: Y | O209: 无 | P209: 无 | Q209: 无 | R209: Y | S209: Y | T209: Y | U209: Y | V209: Y | W209: Y | X209: 7400
... B237: 47076663- EDC260119001 | C237: 紫光展锐 | D237: 锐迪科微电子（上海）有限公司 | E237: U_exp_ 财务费用 | F237: 2025/12/31 | G237: 单体 | H237: 所有PSP | I237: 46157 | J237: lucine lou | K237: Y | L237: N/A | M237: N/A | N237: N/A | O237: 无 | P237: 无 | Q237: 无 | R237: Y | S237: Y | T237: Y | U237: Y | V237: Y | W237: Y | X237: 4500
B238: 47137340- EDC260527002 | C238: 万帮数字 | D238: 万帮数字能源股份有限公司 | E238: K1_固定资产 | F238: 2026/4/30 | G238: 合并 | H238: 所有PSP | I238: 46191 | J238: jane q wang
B239: 47137340- EDC260527002 | C239: 万帮数字 | D239: 万帮数字能源股份有限公司 | E239: Q1_借款 | F239: 2026/4/30 | G239: 合并 | H239: 所有PSP | I239: 46185 | J239: lucine lou
B240: 47137340- EDC260527002 | C240: 万帮数字 | D240: 万帮数字能源股份有限公司 | E240: U_exp_ VC&VD | F240: 2026/4/30 | G240: 合并 | H240: 所有PSP | I240: 46191 | J240: mengqi mq xu
B241: 47137340- EDC260527002 | C241: 万帮数字 | D241: 万帮数字能源股份有限公司 | E241: U_exp_other（财务费用、资产处置收益和营业外收支） | F241: 2026/4/30 | G241: 合并 | H241: 所有PSP | I241: 46185 | J241: mengqi mq xu

Sheet OS list及缺失PBC
B1: 执行过程中发现的异常事项或需关注事项列示在此处，用于周进度汇报
B2: 序号 | C2: 项目 | D2: Entity | E2: 科目 | F2: OS事项 | G2: 事项分类 | H2: 提出时间 | I2: CSDC负责人 | J2: 是否解决 | K2: 备注
B3: 1 | C3: 紫光展锐 | D3: 展讯通信（上海）有限公司 | E3: K1_固定资产 | F3: 改扩建折旧方法存在问题，OS交付 | G3: 提醒事项：待项目组跟进 | H3: 46041 | I3: mengqi mq xu | J3: Y | K3: 项目组认可该方法，最终交付继续提示 | L3: 3000
B4: 2 | C4: 紫光展锐 | D4: Spreadtrum Communications USA Inc. | E4: K1_固定资产 | F4: TOD资料尚未提供 | G4: OS_PBC | H4: 46154 | I4: mengqi mq xu | L4: 2100
B5: 3 | C5: 紫光展锐 | D5: 展讯通信（上海）有限公司 | E5: U_exp_ 销售费用 | F5: TOD及cut off资料尚未提供 | G5: OS_PBC | H5: 46156 | I5: lucine lou | L5: 3000
B6: 4 | C6: 紫光展锐 | D6: 北京紫光展锐通信技术有限公司 | E6: U_exp_ 销售费用 | F6: TOD资料尚未提供 | G6: OS_PBC | H6: 46156 | I6: lucine lou | L6: 4000
B7: 5 | C7: 紫光展锐 | D7: 展讯通信（上海）有限公司 | E7: U_exp_ 管理费用 | F7: TOD及cut off资料尚未提供 | G7: OS_PBC | H7: 46156 | I7: lucine lou | L7: 3000
B8: 6 | C8: 紫光展锐 | D8: 北京紫光展锐通信技术有限公司 | E8: U_exp_ 管理费用 | F8: TOD资料尚未提供 | G8: OS_PBC | H8: 46156 | I8: lucine lou | L8: 4000
B9: 7 | C9: 紫光展锐 | D9: 展讯半导体（成都）有限公司 | E9: U_exp_ 管理费用 | F9: TOD资料尚未提供 | G9: OS_PBC | H9: 46156 | I9: lucine lou | L9: 9200

Sheet OS事项分类说明
B2: 序号 | C2: 事项分类 | D2: 说明
B3: 1 | C3: OS_CSDC | D3: 预期CSDC可以解决的OS事项
B4: 2 | C4: OS_ET | D4: 预期CSDC无法解决的OS事项，需项目组跟进
B5: 3 | C5: OS_PBC | D5: 资料缺失，待客户提供
B6: 4 | C6: issue | D6: 识别的异常以及异常调整，或是执行标准与SOP有出入的
B7: 5 | C7: 提醒事项：待项目组跟进 | D7: 需项目组完成相关工作/关注相关事项
